enerflow/__init__.py
enerflow/base.py
enerflow/assets/__init__.py
enerflow/assets/pv.py
enerflow/assets/wind.py
enerflow/examples/__init__.py
enerflow/examples/building.py
enerflow/examples/microgrid.py
enerflow/examples/gefcom2014_solar/__init__.py
enerflow/examples/gefcom2014_solar/main.py
enerflow/models/__init__.py
enerflow/models/agent.py
enerflow/models/optimizer.py
enerflow/models/predictor.py
enerflow/models/simulator.py
enerflow/problems/__init__.py
enerflow/problems/checks.py
enerflow/problems/dataset.py
enerflow/problems/environments.py
enerflow/problems/objectives.py
enerflow/problems/problem.py
enerflow/spaces/__init__.py
enerflow/spaces/action.py
enerflow/spaces/base.py
enerflow/spaces/input.py
enerflow/spaces/output.py
enerflow/spaces/state.py
enerflow-0.0.2.dist-info/METADATA
enerflow-0.0.2.dist-info/WHEEL
enerflow-0.0.2.dist-info/top_level.txt
enerflow-0.0.2.dist-info/RECORD
