Metadata-Version: 2.1
Name: enerflow
Version: 0.0.2
Summary: ⚡ Open-source framework for sequential decision problems in the energy domain
Home-page: https://github.com/rebase-energy/enerflow
Author: rebase.energy
Author-email: hello@rebase.energy
License: MIT
Requires-Dist: Sphinx ==7.2.6
Requires-Dist: sphinx-rtd-theme
Requires-Dist: EnergyDataModel
Requires-Dist: nbsphinx
